{
    "packages": {
        "c10b10/wp-cli-deploy": [
            {
                "name": "c10b10/wp-cli-deploy",
                "version": "v1.0.0",
                "version_normalized": "1.0.0.0",
                "source": {
                    "type": "git",
                    "url": "https://github.com/c10b10/wp-cli-deploy.git",
                    "reference": "5e2226b3b5797923fbcf5ccadccaa168328f992e"
                },
                "dist": {
                    "type": "zip",
                    "url": "https://api.github.com/repos/c10b10/wp-cli-deploy/zipball/5e2226b3b5797923fbcf5ccadccaa168328f992e",
                    "reference": "5e2226b3b5797923fbcf5ccadccaa168328f992e",
                    "shasum": ""
                },
                "require": {
                    "php": ">=5.4",
                    "wp-cli/wp-cli": ">=0.14"
                },
                "time": "2014-02-28T13:11:25+00:00",
                "type": "library",
                "autoload": {
                    "files": [
                        "deploy.php"
                    ]
                },
                "license": [
                    "MIT"
                ],
                "authors": [
                    {
                        "name": "Alex Ciobica",
                        "email": "alex.ciobica@gmail.com",
                        "homepage": "http://ciobi.ca"
                    }
                ],
                "description": "Deploys the local WordPress database or the uploads directory to a remote server using ssh.",
                "homepage": "https://github.com/c10b10/wp-cli-deploy",
                "keywords": [
                    "deploy",
                    "dump",
                    "git",
                    "mysql",
                    "uploads",
                    "wordpress",
                    "wp-cli"
                ],
                "support": {
                    "source": "https://github.com/c10b10/wp-cli-deploy/tree/v1.0.0",
                    "issues": "https://github.com/c10b10/wp-cli-deploy/issues"
                }
            }
        ]
    }
}
